shell_proc/__init__.py
shell_proc/__main__.py
shell_proc/__meta__.py
shell_proc/non_blocking_pipe.py
shell_proc/shell.py
shell_proc/__pycache__/__init__.cpython-310.pyc
shell_proc/__pycache__/__init__.cpython-311.pyc
shell_proc/__pycache__/__meta__.cpython-310.pyc
shell_proc/__pycache__/__meta__.cpython-311.pyc
shell_proc/__pycache__/non_blocking_pipe.cpython-310.pyc
shell_proc/__pycache__/non_blocking_pipe.cpython-311.pyc
shell_proc/__pycache__/shell.cpython-310.pyc
shell_proc/__pycache__/shell.cpython-311.pyc
shell_proc-3.0.9.dist-info/LICENSE
shell_proc-3.0.9.dist-info/METADATA
shell_proc-3.0.9.dist-info/WHEEL
shell_proc-3.0.9.dist-info/top_level.txt
shell_proc-3.0.9.dist-info/RECORD
