Metadata-Version: 2.1
Name: shell_proc
Version: 3.0.9
Summary: Continuous shell process
Home-page: https://github.com/justengel/shell_proc
Download-URL: https://github.com/justengel/shell_proc/archive/v3.0.9.tar.gz
Author: Justin Engel
Author-email: jtengel08@gmail.com
License: Proprietary
Keywords: shell bash subprocess sh
Platform: any
Classifier: Programming Language :: Python
Classifier: Programming Language :: Python :: 3
Classifier: Operating System :: OS Independent
License-File: LICENSE
